Workbook
Name Target: Lookup!$A$2:$B$7

Sheet Sales
A1: OrderID | B1: OrderDate | C1: StoreID | D1: ProductID | E1: Qty | F1: ProductName | G1: Category | H1: UnitPrice | I1: UnitCost | J1: Region | K1: Revenue | L1: Profit | M1: Margin | N1: Margin Flag | O1: Order Size | P1: Review | Q1: Bulk | R1: Target Margin | S1: Below Target
A2: ORD10197 | B2: 46204 | C2: S02 | D2: P103 | E2: 2 | F2: =_xlfn.XLOOKUP(D2, Products!$A$2:$A$21, Products!$B$2:$B$21, "Not Found") -> Gaming Mouse | G2: =_xlfn.XLOOKUP(D2, Products!$A$2:$A$21, Products!$C$2:$C$21,"Not Found") -> Accessories | H2: =_xlfn.XLOOKUP(D2, Products!$A$2:$A$21, Products!$E$2:$E$21, 0) -> 89 | I2: =_xlfn.XLOOKUP(D2, Products!$A$2:$A$21, Products!$F$2:$F$21,0) -> 41 | J2: =_xlfn.XLOOKUP(C2, Stores!$A$2:$A$7, Stores!$D$2:$D$7) -> Sydney West | K2: =E2*H2 -> 178 | L2: =K2 - (E2 * I2) -> 96 | M2: =IF(Table1[[#This Row],[Revenue]]=0, "", Table1[[#This Row],[Profit]]/Table1[[#This Row],[Revenue]]) -> 0.53932584 | N2: =IF(Table1[[#This Row],[Margin]]="", "check", IF(Table1[[#This Row],[Margin]]<0.2, "Low", "OK")) -> OK | O2: {=_xlfn.IFS(Table1[[#This Row],[Revenue]]=0, "Check", Table1[[#This Row],[Revenue]]>=1000, "Large", Table1[[#This Row],[Revenue]]>=200, "Medium", TRUE, "Small")} -> Small | P2: =IF(AND(Table1[[#This Row],[Margin Flag]]="Low", Table1[[#This Row],[Revenue]]>1000), "Review", "") | Q2: =IF(OR(Table1[[#This Row],[Qty]]>=5,Table1[[#This Row],[Order Size]] = "Large" ), "Bulk", "") | R2: =_xlfn.XLOOKUP(G2, Lookup!$A$2:$A$7, Lookup!$B$2:$B$7, "") -> 0.25 | S2: =IF(Table1[[#This Row],[Margin]]<Table1[[#This Row],[Target Margin]], "Yes", "")
A3: ORD10210 | B3: 46204 | C3: S03 | D3: P108 | E3: 1 | F3: =_xlfn.XLOOKUP(D3, Products!$A$2:$A$21, Products!$B$2:$B$21, "Not Found") -> Wireless Earbuds | G3: =_xlfn.XLOOKUP(D3, Products!$A$2:$A$21, Products!$C$2:$C$21,"not found") -> Audio | H3: =_xlfn.XLOOKUP(D3, Products!$A$2:$A$21, Products!$E$2:$E$21, 0) -> 249 | I3: =_xlfn.XLOOKUP(D3, Products!$A$2:$A$21, Products!$F$2:$F$21,0) -> 140 | J3: =_xlfn.XLOOKUP(C3, Stores!$A$2:$A$7, Stores!$D$2:$D$7) -> Sydney East | K3: =E3*H3 -> 249 | L3: =K3 - (E3 * I3) -> 109 | M3: =IF(Table1[[#This Row],[Revenue]]=0, "", Table1[[#This Row],[Profit]]/Table1[[#This Row],[Revenue]]) -> 0.437751 | N3: =IF(Table1[[#This Row],[Margin]]="", "check", IF(Table1[[#This Row],[Margin]]<0.2, "Low", "OK")) -> OK | O3: {=_xlfn.IFS(Table1[[#This Row],[Revenue]]=0, "Check", Table1[[#This Row],[Revenue]]>=1000, "Large", Table1[[#This Row],[Revenue]]>=200, "Medium", TRUE, "Small")} -> Medium | P3: =IF(AND(Table1[[#This Row],[Margin Flag]]="Low", Table1[[#This Row],[Revenue]]>1000), "Review", "") | Q3: =IF(OR(Table1[[#This Row],[Qty]]>=5,Table1[[#This Row],[Order Size]] = "Large" ), "Bulk", "") | R3: =_xlfn.XLOOKUP(G3, Lookup!$A$2:$A$7, Lookup!$B$2:$B$7, "") -> 0.25 | S3: =IF(Table1[[#This Row],[Margin]]<Table1[[#This Row],[Target Margin]], "Yes", "")
A4: ORD10254 | B4: 46204 | C4: S04 | D4: P110 | E4: 1 | F4: =_xlfn.XLOOKUP(D4, Products!$A$2:$A$21, Products!$B$2:$B$21, "Not Found") -> Bluetooth Speaker | G4: =_xlfn.XLOOKUP(D4, Products!$A$2:$A$21, Products!$C$2:$C$21,"not found") -> Audio | H4: =_xlfn.XLOOKUP(D4, Products!$A$2:$A$21, Products!$E$2:$E$21, 0) -> 179 | I4: =_xlfn.XLOOKUP(D4, Products!$A$2:$A$21, Products!$F$2:$F$21,0) -> 95 | J4: =_xlfn.XLOOKUP(C4, Stores!$A$2:$A$7, Stores!$D$2:$D$7) -> Sydney North | K4: =E4*H4 -> 179 | L4: =K4 - (E4 * I4) -> 84 | M4: =IF(Table1[[#This Row],[Revenue]]=0, "", Table1[[#This Row],[Profit]]/Table1[[#This Row],[Revenue]]) -> 0.46927374 | N4: =IF(Table1[[#This Row],[Margin]]="", "check", IF(Table1[[#This Row],[Margin]]<0.2, "Low", "OK")) -> OK | O4: {=_xlfn.IFS(Table1[[#This Row],[Revenue]]=0, "Check", Table1[[#This Row],[Revenue]]>=1000, "Large", Table1[[#This Row],[Revenue]]>=200, "Medium", TRUE, "Small")} -> Small | P4: =IF(AND(Table1[[#This Row],[Margin Flag]]="Low", Table1[[#This Row],[Revenue]]>1000), "Review", "") | Q4: =IF(OR(Table1[[#This Row],[Qty]]>=5,Table1[[#This Row],[Order Size]] = "Large" ), "Bulk", "") | R4: =_xlfn.XLOOKUP(G4, Lookup!$A$2:$A$7, Lookup!$B$2:$B$7, "") -> 0.25 | S4: =IF(Table1[[#This Row],[Margin]]<Table1[[#This Row],[Target Margin]], "Yes", "")
A5: ORD10317 | B5: 46204 | C5: S06 | D5: P120 | E5: 2 | F5: =_xlfn.XLOOKUP(D5, Products!$A$2:$A$21, Products!$B$2:$B$21, "Not Found") -> Video Game | G5: =_xlfn.XLOOKUP(D5, Products!$A$2:$A$21, Products!$C$2:$C$21,"not found") -> Gaming | H5: =_xlfn.XLOOKUP(D5, Products!$A$2:$A$21, Products!$E$2:$E$21, 0) -> 79 | I5: =_xlfn.XLOOKUP(D5, Products!$A$2:$A$21, Products!$F$2:$F$21,0) -> 52 | J5: =_xlfn.XLOOKUP(C5, Stores!$A$2:$A$7, Stores!$D$2:$D$7) -> Sydney West | K5: =E5*H5 -> 158 | L5: =K5 - (E5 * I5) -> 54 | M5: =IF(Table1[[#This Row],[Revenue]]=0, "", Table1[[#This Row],[Profit]]/Table1[[#This Row],[Revenue]]) -> 0.34177215 | N5: =IF(Table1[[#This Row],[Margin]]="", "check", IF(Table1[[#This Row],[Margin]]<0.2, "Low", "OK")) -> OK | O5: {=_xlfn.IFS(Table1[[#This Row],[Revenue]]=0, "Check", Table1[[#This Row],[Revenue]]>=1000, "Large", Table1[[#This Row],[Revenue]]>=200, "Medium", TRUE, "Small")} -> Small | P5: =IF(AND(Table1[[#This Row],[Margin Flag]]="Low", Table1[[#This Row],[Revenue]]>1000), "Review", "") | Q5: =IF(OR(Table1[[#This Row],[Qty]]>=5,Table1[[#This Row],[Order Size]] = "Large" ), "Bulk", "") | R5: =_xlfn.XLOOKUP(G5, Lookup!$A$2:$A$7, Lookup!$B$2:$B$7, "") -> 0.08 | S5: =IF(Table1[[#This Row],[Margin]]<Table1[[#This Row],[Target Margin]], "Yes", "")
A6: ORD10330 | B6: 46204 | C6: S01 | D6: P110 | E6: 1 | F6: =_xlfn.XLOOKUP(D6, Products!$A$2:$A$21, Products!$B$2:$B$21, "Not Found") -> Bluetooth Speaker | G6: =_xlfn.XLOOKUP(D6, Products!$A$2:$A$21, Products!$C$2:$C$21,"not found") -> Audio | H6: =_xlfn.XLOOKUP(D6, Products!$A$2:$A$21, Products!$E$2:$E$21, 0) -> 179 | I6: =_xlfn.XLOOKUP(D6, Products!$A$2:$A$21, Products!$F$2:$F$21,0) -> 95 | J6: =_xlfn.XLOOKUP(C6, Stores!$A$2:$A$7, Stores!$D$2:$D$7) -> Sydney South | K6: =E6*H6 -> 179 | L6: =K6 - (E6 * I6) -> 84 | M6: =IF(Table1[[#This Row],[Revenue]]=0, "", Table1[[#This Row],[Profit]]/Table1[[#This Row],[Revenue]]) -> 0.46927374 | N6: =IF(Table1[[#This Row],[Margin]]="", "check", IF(Table1[[#This Row],[Margin]]<0.2, "Low", "OK")) -> OK | O6: {=_xlfn.IFS(Table1[[#This Row],[Revenue]]=0, "Check", Table1[[#This Row],[Revenue]]>=1000, "Large", Table1[[#This Row],[Revenue]]>=200, "Medium", TRUE, "Small")} -> Small | P6: =IF(AND(Table1[[#This Row],[Margin Flag]]="Low", Table1[[#This Row],[Revenue]]>1000), "Review", "") | Q6: =IF(OR(Table1[[#This Row],[Qty]]>=5,Table1[[#This Row],[Order Size]] = "Large" ), "Bulk", "") | R6: =_xlfn.XLOOKUP(G6, Lookup!$A$2:$A$7, Lookup!$B$2:$B$7, "") -> 0.25 | S6: =IF(Table1[[#This Row],[Margin]]<Table1[[#This Row],[Target Margin]], "Yes", "")
A7: ORD10350 | B7: 46204 | C7: S01 | D7: P110 | E7: 1 | F7: =_xlfn.XLOOKUP(D7, Products!$A$2:$A$21, Products!$B$2:$B$21, "Not Found") -> Bluetooth Speaker | G7: =_xlfn.XLOOKUP(D7, Products!$A$2:$A$21, Products!$C$2:$C$21,"not found") -> Audio | H7: =_xlfn.XLOOKUP(D7, Products!$A$2:$A$21, Products!$E$2:$E$21, 0) -> 179 | I7: =_xlfn.XLOOKUP(D7, Products!$A$2:$A$21, Products!$F$2:$F$21,0) -> 95 | J7: =_xlfn.XLOOKUP(C7, Stores!$A$2:$A$7, Stores!$D$2:$D$7) -> Sydney South | K7: =E7*H7 -> 179 | L7: =K7 - (E7 * I7) -> 84 | M7: =IF(Table1[[#This Row],[Revenue]]=0, "", Table1[[#This Row],[Profit]]/Table1[[#This Row],[Revenue]]) -> 0.46927374 | N7: =IF(Table1[[#This Row],[Margin]]="", "check", IF(Table1[[#This Row],[Margin]]<0.2, "Low", "OK")) -> OK | O7: {=_xlfn.IFS(Table1[[#This Row],[Revenue]]=0, "Check", Table1[[#This Row],[Revenue]]>=1000, "Large", Table1[[#This Row],[Revenue]]>=200, "Medium", TRUE, "Small")} -> Small | P7: =IF(AND(Table1[[#This Row],[Margin Flag]]="Low", Table1[[#This Row],[Revenue]]>1000), "Review", "") | Q7: =IF(OR(Table1[[#This Row],[Qty]]>=5,Table1[[#This Row],[Order Size]] = "Large" ), "Bulk", "") | R7: =_xlfn.XLOOKUP(G7, Lookup!$A$2:$A$7, Lookup!$B$2:$B$7, "") -> 0.25 | S7: =IF(Table1[[#This Row],[Margin]]<Table1[[#This Row],[Target Margin]], "Yes", "")
A8: ORD10372 | B8: 46204 | C8: S03 | D8: P116 | E8: 4 | F8: =_xlfn.XLOOKUP(D8, Products!$A$2:$A$21, Products!$B$2:$B$21, "Not Found") -> Phone Case | G8: =_xlfn.XLOOKUP(D8, Products!$A$2:$A$21, Products!$C$2:$C$21,"not found") -> Accessories | H8: =_xlfn.XLOOKUP(D8, Products!$A$2:$A$21, Products!$E$2:$E$21, 0) -> 39 | I8: =_xlfn.XLOOKUP(D8, Products!$A$2:$A$21, Products!$F$2:$F$21,0) -> 9 | J8: =_xlfn.XLOOKUP(C8, Stores!$A$2:$A$7, Stores!$D$2:$D$7) -> Sydney East | K8: =E8*H8 -> 156 | L8: =K8 - (E8 * I8) -> 120 | M8: =IF(Table1[[#This Row],[Revenue]]=0, "", Table1[[#This Row],[Profit]]/Table1[[#This Row],[Revenue]]) -> 0.76923077 | N8: =IF(Table1[[#This Row],[Margin]]="", "check", IF(Table1[[#This Row],[Margin]]<0.2, "Low", "OK")) -> OK | O8: {=_xlfn.IFS(Table1[[#This Row],[Revenue]]=0, "Check", Table1[[#This Row],[Revenue]]>=1000, "Large", Table1[[#This Row],[Revenue]]>=200, "Medium", TRUE, "Small")} -> Small | P8: =IF(AND(Table1[[#This Row],[Margin Flag]]="Low", Table1[[#This Row],[Revenue]]>1000), "Review", "") | Q8: =IF(OR(Table1[[#This Row],[Qty]]>=5,Table1[[#This Row],[Order Size]] = "Large" ), "Bulk", "") | R8: =_xlfn.XLOOKUP(G8, Lookup!$A$2:$A$7, Lookup!$B$2:$B$7, "") -> 0.25 | S8: =IF(Table1[[#This Row],[Margin]]<Table1[[#This Row],[Target Margin]], "Yes", "")
A9: ORD10461 | B9: 46204 | C9: S01 | D9: P103 | E9: 1 | F9: =_xlfn.XLOOKUP(D9, Products!$A$2:$A$21, Products!$B$2:$B$21, "Not Found") -> Gaming Mouse | G9: =_xlfn.XLOOKUP(D9, Products!$A$2:$A$21, Products!$C$2:$C$21,"not found") -> Accessories | H9: =_xlfn.XLOOKUP(D9, Products!$A$2:$A$21, Products!$E$2:$E$21, 0) -> 89 | I9: =_xlfn.XLOOKUP(D9, Products!$A$2:$A$21, Products!$F$2:$F$21,0) -> 41 | J9: =_xlfn.XLOOKUP(C9, Stores!$A$2:$A$7, Stores!$D$2:$D$7) -> Sydney South | K9: =E9*H9 -> 89 | L9: =K9 - (E9 * I9) -> 48 | M9: =IF(Table1[[#This Row],[Revenue]]=0, "", Table1[[#This Row],[Profit]]/Table1[[#This Row],[Revenue]]) -> 0.53932584 | N9: =IF(Table1[[#This Row],[Margin]]="", "check", IF(Table1[[#This Row],[Margin]]<0.2, "Low", "OK")) -> OK | O9: {=_xlfn.IFS(Table1[[#This Row],[Revenue]]=0, "Check", Table1[[#This Row],[Revenue]]>=1000, "Large", Table1[[#This Row],[Revenue]]>=200, "Medium", TRUE, "Small")} -> Small | P9: =IF(AND(Table1[[#This Row],[Margin Flag]]="Low", Table1[[#This Row],[Revenue]]>1000), "Review", "") | Q9: =IF(OR(Table1[[#This Row],[Qty]]>=5,Table1[[#This Row],[Order Size]] = "Large" ), "Bulk", "") | R9: =_xlfn.XLOOKUP(G9, Lookup!$A$2:$A$7, Lookup!$B$2:$B$7, "") -> 0.25 | S9: =IF(Table1[[#This Row],[Margin]]<Table1[[#This Row],[Target Margin]], "Yes", "")
A10: ORD10497 | B10: 46204 | C10: S03 | D10: P117 | E10: 1 | F10: =_xlfn.XLOOKUP(D10, Products!$A$2:$A$21, Products!$B$2:$B$21, "Not Found") -> USB-C Charger | G10: =_xlfn.XLOOKUP(D10, Products!$A$2:$A$21, Products!$C$2:$C$21,"not found") -> Accessories | H10: =_xlfn.XLOOKUP(D10, Products!$A$2:$A$21, Products!$E$2:$E$21, 0) -> 49 | I10: =_xlfn.XLOOKUP(D10, Products!$A$2:$A$21, Products!$F$2:$F$21,0) -> 14 | J10: =_xlfn.XLOOKUP(C10, Stores!$A$2:$A$7, Stores!$D$2:$D$7) -> Sydney East | K10: =E10*H10 -> 49 | L10: =K10 - (E10 * I10) -> 35 | M10: =IF(Table1[[#This Row],[Revenue]]=0, "", Table1[[#This Row],[Profit]]/Table1[[#This Row],[Revenue]]) -> 0.71428571 | N10: =IF(Table1[[#This Row],[Margin]]="", "check", IF(Table1[[#This Row],[Margin]]<0.2, "Low", "OK")) -> OK | O10: {=_xlfn.IFS(Table1[[#This Row],[Revenue]]=0, "Check", Table1[[#This Row],[Revenue]]>=1000, "Large", Table1[[#This Row],[Revenue]]>=200, "Medium", TRUE, "Small")} -> Small | P10: =IF(AND(Table1[[#This Row],[Margin Flag]]="Low", Table1[[#This Row],[Revenue]]>1000), "Review", "") | Q10: =IF(OR(Table1[[#This Row],[Qty]]>=5,Table1[[#This Row],[Order Size]] = "Large" ), "Bulk", "") | R10: =_xlfn.XLOOKUP(G10, Lookup!$A$2:$A$7, Lookup!$B$2:$B$7, "") -> 0.25 | S10: =IF(Table1[[#This Row],[Margin]]<Table1[[#This Row],[Target Margin]], "Yes", "")
A11: ORD10529 | B11: 46204 | C11: S02 | D11: P103 | E11: 1 | F11: =_xlfn.XLOOKUP(D11, Products!$A$2:$A$21, Products!$B$2:$B$21, "Not Found") -> Gaming Mouse | G11: =_xlfn.XLOOKUP(D11, Products!$A$2:$A$21, Products!$C$2:$C$21,"not found") -> Accessories | H11: =_xlfn.XLOOKUP(D11, Products!$A$2:$A$21, Products!$E$2:$E$21, 0) -> 89 | I11: =_xlfn.XLOOKUP(D11, Products!$A$2:$A$21, Products!$F$2:$F$21,0) -> 41 | J11: =_xlfn.XLOOKUP(C11, Stores!$A$2:$A$7, Stores!$D$2:$D$7) -> Sydney West | K11: =E11*H11 -> 89 | L11: =K11 - (E11 * I11) -> 48 | M11: =IF(Table1[[#This Row],[Revenue]]=0, "", Table1[[#This Row],[Profit]]/Table1[[#This Row],[Revenue]]) -> 0.53932584 | N11: =IF(Table1[[#This Row],[Margin]]="", "check", IF(Table1[[#This Row],[Margin]]<0.2, "Low", "OK")) -> OK | O11: {=_xlfn.IFS(Table1[[#This Row],[Revenue]]=0, "Check", Table1[[#This Row],[Revenue]]>=1000, "Large", Table1[[#This Row],[Revenue]]>=200, "Medium", TRUE, "Small")} -> Small | P11: =IF(AND(Table1[[#This Row],[Margin Flag]]="Low", Table1[[#This Row],[Revenue]]>1000), "Review", "") | Q11: =IF(OR(Table1[[#This Row],[Qty]]>=5,Table1[[#This Row],[Order Size]] = "Large" ), "Bulk", "") | R11: =_xlfn.XLOOKUP(G11, Lookup!$A$2:$A$7, Lookup!$B$2:$B$7, "") -> 0.25 | S11: =IF(Table1[[#This Row],[Margin]]<Table1[[#This Row],[Target Margin]], "Yes", "")
A12: ORD10566 | B12: 46204 | C12: S03 | D12: P108 | E12: 1 | F12: =_xlfn.XLOOKUP(D12, Products!$A$2:$A$21, Products!$B$2:$B$21, "Not Found") -> Wireless Earbuds | G12: =_xlfn.XLOOKUP(D12, Products!$A$2:$A$21, Products!$C$2:$C$21,"not found") -> Audio | H12: =_xlfn.XLOOKUP(D12, Products!$A$2:$A$21, Products!$E$2:$E$21, 0) -> 249 | I12: =_xlfn.XLOOKUP(D12, Products!$A$2:$A$21, Products!$F$2:$F$21,0) -> 140 | J12: =_xlfn.XLOOKUP(C12, Stores!$A$2:$A$7, Stores!$D$2:$D$7) -> Sydney East | K12: =E12*H12 -> 249 | L12: =K12 - (E12 * I12) -> 109 | M12: =IF(Table1[[#This Row],[Revenue]]=0, "", Table1[[#This Row],[Profit]]/Table1[[#This Row],[Revenue]]) -> 0.437751 | N12: =IF(Table1[[#This Row],[Margin]]="", "check", IF(Table1[[#This Row],[Margin]]<0.2, "Low", "OK")) -> OK | O12: {=_xlfn.IFS(Table1[[#This Row],[Revenue]]=0, "Check", Table1[[#This Row],[Revenue]]>=1000, "Large", Table1[[#This Row],[Revenue]]>=200, "Medium", TRUE, "Small")} -> Medium | P12: =IF(AND(Table1[[#This Row],[Margin Flag]]="Low", Table1[[#This Row],[Revenue]]>1000), "Review", "") | Q12: =IF(OR(Table1[[#This Row],[Qty]]>=5,Table1[[#This Row],[Order Size]] = "Large" ), "Bulk", "") | R12: =_xlfn.XLOOKUP(G12, Lookup!$A$2:$A$7, Lookup!$B$2:$B$7, "") -> 0.25 | S12: =IF(Table1[[#This Row],[Margin]]<Table1[[#This Row],[Target Margin]], "Yes", "")
A13: ORD10166 | B13: 46205 | C13: S06 | D13: P120 | E13: 1 | F13: =_xlfn.XLOOKUP(D13, Products!$A$2:$A$21, Products!$B$2:$B$21, "Not Found") -> Video Game | G13: =_xlfn.XLOOKUP(D13, Products!$A$2:$A$21, Products!$C$2:$C$21,"not found") -> Gaming | H13: =_xlfn.XLOOKUP(D13, Products!$A$2:$A$21, Products!$E$2:$E$21, 0) -> 79 | I13: =_xlfn.XLOOKUP(D13, Products!$A$2:$A$21, Products!$F$2:$F$21,0) -> 52 | J13: =_xlfn.XLOOKUP(C13, Stores!$A$2:$A$7, Stores!$D$2:$D$7) -> Sydney West | K13: =E13*H13 -> 79 | L13: =K13 - (E13 * I13) -> 27 | M13: =IF(Table1[[#This Row],[Revenue]]=0, "", Table1[[#This Row],[Profit]]/Table1[[#This Row],[Revenue]]) -> 0.34177215 | N13: =IF(Table1[[#This Row],[Margin]]="", "check", IF(Table1[[#This Row],[Margin]]<0.2, "Low", "OK")) -> OK | O13: {=_xlfn.IFS(Table1[[#This Row],[Revenue]]=0, "Check", Table1[[#This Row],[Revenue]]>=1000, "Large", Table1[[#This Row],[Revenue]]>=200, "Medium", TRUE, "Small")} -> Small | P13: =IF(AND(Table1[[#This Row],[Margin Flag]]="Low", Table1[[#This Row],[Revenue]]>1000), "Review", "") | Q13: =IF(OR(Table1[[#This Row],[Qty]]>=5,Table1[[#This Row],[Order Size]] = "Large" ), "Bulk", "") | R13: =_xlfn.XLOOKUP(G13, Lookup!$A$2:$A$7, Lookup!$B$2:$B$7, "") -> 0.08 | S13: =IF(Table1[[#This Row],[Margin]]<Table1[[#This Row],[Target Margin]], "Yes", "")
A14: ORD10263 | B14: 46205 | C14: S03 | D14: P115 | E14: 1 | F14: =_xlfn.XLOOKUP(D14, Products!$A$2:$A$21, Products!$B$2:$B$21, "Not Found") -> Console Controller | G14: =_xlfn.XLOOKUP(D14, Products!$A$2:$A$21, Products!$C$2:$C$21,"not found") -> Gaming | H14: =_xlfn.XLOOKUP(D14, Products!$A$2:$A$21, Products!$E$2:$E$21, 0) -> 99 | I14: =_xlfn.XLOOKUP(D14, Products!$A$2:$A$21, Products!$F$2:$F$21,0) -> 58 | J14: =_xlfn.XLOOKUP(C14, Stores!$A$2:$A$7, Stores!$D$2:$D$7) -> Sydney East | K14: =E14*H14 -> 99 | L14: =K14 - (E14 * I14) -> 41 | M14: =IF(Table1[[#This Row],[Revenue]]=0, "", Table1[[#This Row],[Profit]]/Table1[[#This Row],[Revenue]]) -> 0.41414141 | N14: =IF(Table1[[#This Row],[Margin]]="", "check", IF(Table1[[#This Row],[Margin]]<0.2, "Low", "OK")) -> OK | O14: {=_xlfn.IFS(Table1[[#This Row],[Revenue]]=0, "Check", Table1[[#This Row],[Revenue]]>=1000, "Large", Table1[[#This Row],[Revenue]]>=200, "Medium", TRUE, "Small")} -> Small | P14: =IF(AND(Table1[[#This Row],[Margin Flag]]="Low", Table1[[#This Row],[Revenue]]>1000), "Review", "") | Q14: =IF(OR(Table1[[#This Row],[Qty]]>=5,Table1[[#This Row],[Order Size]] = "Large" ), "Bulk", "") | R14: =_xlfn.XLOOKUP(G14, Lookup!$A$2:$A$7, Lookup!$B$2:$B$7, "") -> 0.08 | S14: =IF(Table1[[#This Row],[Margin]]<Table1[[#This Row],[Target Margin]], "Yes", "")
... A601: ORD10577 | B601: 46295 | C601: S02 | D601: P103 | E601: 2 | F601: =_xlfn.XLOOKUP(D601, Products!$A$2:$A$21, Products!$B$2:$B$21, "Not Found") -> Gaming Mouse | G601: =_xlfn.XLOOKUP(D601, Products!$A$2:$A$21, Products!$C$2:$C$21,"not found") -> Accessories | H601: =_xlfn.XLOOKUP(D601, Products!$A$2:$A$21, Products!$E$2:$E$21, 0) -> 89 | I601: =_xlfn.XLOOKUP(D601, Products!$A$2:$A$21, Products!$F$2:$F$21,0) -> 41 | J601: =_xlfn.XLOOKUP(C601, Stores!$A$2:$A$7, Stores!$D$2:$D$7) -> Sydney West | K601: =E601*H601 -> 178 | L601: =K601 - (E601 * I601) -> 96 | M601: =IF(Table1[[#This Row],[Revenue]]=0, "", Table1[[#This Row],[Profit]]/Table1[[#This Row],[Revenue]]) -> 0.53932584 | N601: =IF(Table1[[#This Row],[Margin]]="", "check", IF(Table1[[#This Row],[Margin]]<0.2, "Low", "OK")) -> OK | O601: {=_xlfn.IFS(Table1[[#This Row],[Revenue]]=0, "Check", Table1[[#This Row],[Revenue]]>=1000, "Large", Table1[[#This Row],[Revenue]]>=200, "Medium", TRUE, "Small")} -> Small | P601: =IF(AND(Table1[[#This Row],[Margin Flag]]="Low", Table1[[#This Row],[Revenue]]>1000), "Review", "") | Q601: =IF(OR(Table1[[#This Row],[Qty]]>=5,Table1[[#This Row],[Order Size]] = "Large" ), "Bulk", "") | R601: =_xlfn.XLOOKUP(G601, Lookup!$A$2:$A$7, Lookup!$B$2:$B$7, "") -> 0.25 | S601: =IF(Table1[[#This Row],[Margin]]<Table1[[#This Row],[Target Margin]], "Yes", "")
J610: Total | K610: =SUM(K2:K601) -> 317546 | L610: =SUM(L2:L601) -> 92222
N618: check low | O618: =COUNTIF(N2:N601,"low") -> 11
N619: Check | O619: =COUNTIF(O:O, "Check") -> 4
N620: Small | O620: =COUNTIF(O:O, "Small") -> 321
N621: Medium | O621: =COUNTIF(O:O, "Medium") -> 156
N622: Large | O622: =COUNTIF(O:O, "Large") -> 119
N623: T Check | O623: =SUMIF(Table1[Order Size], "Check", Table1[Revenue]) -> 0 | P623: =0 -> 0
N624: T Small | O624: =SUMIF(Table1[Order Size], "Small", Table1[Revenue]) -> 32300 | P624: =(O624/K610)*100 -> 10.171755
N625: T Medium | O625: =SUMIF(Table1[Order Size], "Medium", Table1[Revenue]) -> 75829 | P625: =(O625/K610)*100 -> 23.87969
N626: T Large | O626: =SUMIF(Table1[Order Size], "Large", Table1[Revenue]) -> 209417 | P626: =(O626/K610)*100 -> 65.948555
N627: P O S | O627: =O620/6 -> 53.5
N628: P O M | O628: =O621/6 -> 26
N629: P O L | O629: =O622/6 -> 19.833333
N630: P O C | O630: =O619/6 -> 0.66666667
N631: C review | O631: =COUNTIF(Table1[Review], "Review") -> 2
N632: C bulk | O632: =COUNTIF(Table1[Bulk], "Bulk") -> 119
N633: C below margin | O633: =COUNTIF(Table1[Below Target], "Yes") -> 117

Sheet Lookup
A1: Catagory | B1: Target Margin
A2: Accessories | B2: 0.25
A3: Audio | B3: 0.25
A4: Gaming | B4: 0.08
A5: Phones | B5: 0.25
A6: Computers | B6: 0.25
A7: TV | B7: 0.25

Sheet Products
A1: ProductID | B1: ProductName | C1: Category | D1: Brand | E1: UnitPrice | F1: UnitCost
A2: P101 | B2: Laptop 14in | C2: Computers | D2: Lenova | E2: 1199 | F2: 930
A3: P102 | B3: Laptop 16in | C3: Computers | D3: Azus | E3: 1799 | F3: 1390
A4: P103 | B4: Gaming Mouse | C4: Accessories | D4: Logitek | E4: 89 | F4: 41
A5: P104 | B5: Mech Keyboard | C5: Accessories | D5: Logitek | E5: 149 | F5: 72
A6: P105 | B6: 27in Monitor | C6: Computers | D6: Samsong | E6: 399 | F6: 290
A7: P106 | B7: Smartphone 128GB | C7: Phones | D7: Samsong | E7: 1099 | F7: 860
A8: P107 | B8: Smartphone 256GB | C8: Phones | D8: Appel | E8: 1499 | F8: 1180
A9: P108 | B9: Wireless Earbuds | C9: Audio | D9: Sonee | E9: 249 | F9: 140
A10: P109 | B10: Over-Ear Headphones | C10: Audio | D10: Sonee | E10: 499 | F10: 310
A11: P110 | B11: Bluetooth Speaker | C11: Audio | D11: JBN | E11: 179 | F11: 95
A12: P111 | B12: 55in TV | C12: TV | D12: LGG | E12: 1299 | F12: 980
A13: P112 | B13: 65in TV | C13: TV | D13: Samsong | E13: 1999 | F13: 1520
... A21: P120 | B21: Video Game | C21: Gaming | D21: Various | E21: 79 | F21: 52

Sheet Stores
A1: StoreID | B1: StoreName | C1: State | D1: Region
A2: S01 | B2: Rockdale | C2: NSW | D2: Sydney South
A3: S02 | B3: Parramatta | C3: NSW | D3: Sydney West
A4: S03 | B4: Bondi Junction | C4: NSW | D4: Sydney East
A5: S04 | B5: Chatswood | C5: NSW | D5: Sydney North
A6: S05 | B6: Hurstville | C6: NSW | D6: Sydney South
A7: S06 | B7: Penrith | C7: NSW | D7: Sydney West
